finam_netcdf/__init__.py
finam_netcdf/_version.py
finam_netcdf/reader.py
finam_netcdf/tools.py
finam_netcdf/writer.py
finam_netcdf-0.2.0.dist-info/METADATA
finam_netcdf-0.2.0.dist-info/WHEEL
finam_netcdf-0.2.0.dist-info/licenses/AUTHORS.md
finam_netcdf-0.2.0.dist-info/licenses/COPYING
finam_netcdf-0.2.0.dist-info/licenses/COPYING.LESSER
finam_netcdf-0.2.0.dist-info/licenses/LICENSE.md
finam_netcdf-0.2.0.dist-info/RECORD
